benchmarking_asv/__init__.py
benchmarking_asv/_version.py
benchmarking_asv/example_module.py
benchmarking_asv-0.0.6.dist-info/METADATA
benchmarking_asv-0.0.6.dist-info/WHEEL
benchmarking_asv-0.0.6.dist-info/top_level.txt
benchmarking_asv-0.0.6.dist-info/RECORD
