Metadata-Version: 2.1
Name: benchmarking-asv
Version: 0.0.6
Author-email: Sandro Campos <scampos@andrew.cmu.edu>
Project-URL: Source Code, https://github.com/lincc-frameworks/benchmarking-asv
Classifier: Development Status :: 4 - Beta
Classifier: Intended Audience :: Developers
Classifier: Intended Audience :: Science/Research
Classifier: Operating System :: OS Independent
Classifier: Programming Language :: Python
Requires-Python: >=3.9
Requires-Dist: dask[complete] >=2024.3.0
Requires-Dist: deprecated
Requires-Dist: hats >=0.4
Requires-Dist: ipykernel
Requires-Dist: numpy
Requires-Dist: pandas
Requires-Dist: pyarrow
Requires-Dist: pyyaml
Requires-Dist: scipy
Requires-Dist: tqdm
Requires-Dist: universal-pathlib
Provides-Extra: dev
Requires-Dist: asv ==0.6.1 ; extra == 'dev'
Requires-Dist: jupyter ; extra == 'dev'
Requires-Dist: pre-commit ; extra == 'dev'
Requires-Dist: pylint ; extra == 'dev'
Requires-Dist: pytest ; extra == 'dev'
Requires-Dist: pytest-cov ; extra == 'dev'
